exasol/extensions/licenses/__init__.cpython-310-x86_64-linux-gnu.so
exasol/extensions/licenses/version.cpython-310-x86_64-linux-gnu.so
exasol/extensions/licenses/api/cli_interface.cpython-310-x86_64-linux-gnu.so
exasol/extensions/licenses/binary_image/__init__.cpython-310-x86_64-linux-gnu.so
exasol/extensions/licenses/binary_image/binary_distribution.cpython-310-x86_64-linux-gnu.so
exasol/extensions/licenses/binary_image/nox_tasks.cpython-310-x86_64-linux-gnu.so
exasol/extensions/licenses/binary_image/poetry_to_hatch.cpython-310-x86_64-linux-gnu.so
exasol/extensions/licenses/cli/cli.cpython-310-x86_64-linux-gnu.so
exasol/extensions/licenses/cli/main.cpython-310-x86_64-linux-gnu.so
exasol/extensions/licenses/cli/commands/__init__.cpython-310-x86_64-linux-gnu.so
exasol/extensions/licenses/cli/commands/_shared.cpython-310-x86_64-linux-gnu.so
exasol/extensions/licenses/cli/commands/create_certificate.cpython-310-x86_64-linux-gnu.so
exasol/extensions/licenses/cli/commands/create_private_key.cpython-310-x86_64-linux-gnu.so
exasol/extensions/licenses/cli/commands/sign.cpython-310-x86_64-linux-gnu.so
exasol/extensions/licenses/cli/commands/verify.cpython-310-x86_64-linux-gnu.so
exasol/extensions/licenses/pydantic/model.cpython-310-x86_64-linux-gnu.so
exasol/extensions/licenses/pydantic/pydantic_cython_helper.cpython-310-x86_64-linux-gnu.so
exasol/extensions/licenses/signing/certificates.cpython-310-x86_64-linux-gnu.so
exasol/extensions/licenses/signing/endesive_verifier.cpython-310-x86_64-linux-gnu.so
exasol/extensions/licenses/signing/mime.cpython-310-x86_64-linux-gnu.so
exasol/extensions/licenses/signing/private_keys.cpython-310-x86_64-linux-gnu.so
exasol/extensions/licenses/storage/connections.cpython-310-x86_64-linux-gnu.so
exasol/extensions/licenses/storage/deployment.cpython-310-x86_64-linux-gnu.so
exasol/extensions/licenses/verification/__init__.cpython-310-x86_64-linux-gnu.so
exasol_extension_license_protocol-0.3.0.dist-info/METADATA
exasol_extension_license_protocol-0.3.0.dist-info/WHEEL
exasol_extension_license_protocol-0.3.0.dist-info/RECORD
