Metadata-Version: 2.4
Name: exasol-extension-license-protocol
Version: 0.3.0
Summary: Software License Generator and Validator for closed-source Extensions.
Author-email: Christoph Kuhnke <christoph.kuhnke@exasol.com>
License-Expression: LicenseRef-Proprietary
Keywords: exasol,extension_license_protocol
Requires-Python: <4.0,>=3.10
Requires-Dist: cryptography<46,>=45.0.2
Requires-Dist: humanfriendly<11,>=10.0
Requires-Dist: pydantic<3,>=2.11.4
Requires-Dist: pyhanko-certvalidator<1,>=0.27.0
